{"id":"c1013","number":984,"headline":{"en":"Star Formation Analysis","da":"Stjernedannelsesanalyse"},"content":{"en":"Star Formation Analysis: Scientists have used various algorithms to study different aspects of star formation in molecular clouds. For example, the CLUMPFIND algorithm was used to identify cluster-forming cores in the Vela molecular ridge, while the clfind and gaussclumps algorithms were used to identify star-forming cores in the Perseus molecular cloud. Other algorithms, such as Hi-GAL and a modified blackbody fitting algorithm, were used to characterize the dust temperature and column densities of infrared dark clouds (IRDCs). These algorithms help scientists understand the properties and distributions of different types of cores and clouds in the universe.","da":"Stjernedannelsesanalyse: Forskere har brugt forskellige algoritmer til at studere forskellige aspekter af stjernedannelse i molekylære skyer. For eksempel blev CLUMPFIND-algoritmen brugt til at identificere klynge-dannende kerner i Vela-molekylæråsen, mens clfind- og gaussclumps-algoritmerne blev brugt til at identificere stjernedannende kerner i Perseus-molekylærskyen. Andre algoritmer, såsom Hi-GAL og en modificeret sortlegeme-tilpasningsalgoritme, blev brugt til at karakterisere støvtemperaturen og kolonnedensiteterne af infrarøde mørke skyer (IRDC'er). Disse algoritmer hjælper forskere med at forstå egenskaberne og fordelingen af forskellige typer kerner og skyer i universet."},"bots":{"critic":{"en":null,"da":null},"potential":{"en":null,"da":null}}}