{"id":"c1094","number":1558,"headline":{"en":"Skew correction algorithms","da":"Skråningskorrektionsalgoritmer"},"content":{"en":"Skew correction algorithms: Researchers have developed various algorithms to detect and correct skew in document images. These algorithms are capable of accurately determining the degree of misalignment in a document page and efficiently implementing skew correction. They use techniques such as cross-correlation, hierarchical Hough transform, morphology, statistical analysis, and convex hulls to achieve high precision skew detection and correction.","da":"Skråningskorrektionsalgoritmer: Forskere har udviklet forskellige algoritmer til at opdage og korrigere skråning i dokumentbilleder. Disse algoritmer er i stand til nøjagtigt at bestemme graden af fejljustering i en dokumentside og effektivt implementere skråningskorrektion. De anvender teknikker såsom krydskorrelation, hierarkisk Hough-transform, morfologi, statistisk analyse og konvekse hylstre for at opnå præcis skråningsdetektion og -korrektion."},"bots":{"critic":{"en":null,"da":null},"potential":{"en":null,"da":null}}}