{"id":"c1184","number":1442,"headline":{"en":"Automated systematic reviews","da":"Automatiserede systematiske gennemgange"},"content":{"en":"Automated systematic reviews: Researchers have been exploring the use of algorithms to improve the efficiency of systematic reviews, which involve screening large numbers of research papers. These algorithms, such as Abstrackr and text mining tools, can automate the screening process by predicting the relevance of titles and abstracts. Machine learning and artificial intelligence algorithms are also being used to extend searches, prioritize relevant studies, and extract data from research papers. These advancements have the potential to expedite the review process and improve the accuracy and efficiency of systematic reviews.","da":"Automatiserede systematiske gennemgange: Forskere har undersøgt brugen af algoritmer til at forbedre effektiviteten af systematiske gennemgange, som indebærer at gennemgå et stort antal forskningsartikler. Disse algoritmer, såsom Abstrackr og tekstminingsværktøjer, kan automatisere screeingen ved at forudsige relevansen af titler og abstrakter. Maskinlæring og kunstig intelligens-algoritmer bliver også brugt til at udvide søgninger, prioritere relevante studier og udtrække data fra forskningsartikler. Disse fremskridt har potentiale til at fremskynde gennemgangsprocessen og forbedre nøjagtigheden og effektiviteten af systematiske gennemgange."},"bots":{"critic":{"en":null,"da":null},"potential":{"en":null,"da":null}}}