{"id":"c143","number":707,"headline":{"en":"Reservoir optimization","da":"Reservoiroptimering"},"content":{"en":"Reservoir optimization: Genetic algorithms are being used to optimize the operation of reservoir systems in various ways. These algorithms aim to minimize penalties resulting from water supply issues and low reservoir storage states. They are effective in deriving operating rules for single and multi-reservoir systems, and can even be used for real-time operation and to address the impact of climate change. Overall, genetic algorithms provide a robust and efficient way to optimize the allocation and management of water resources in complex reservoir systems.","da":"Reservoiroptimering: Genetiske algoritmer anvendes til at optimere driften af reservoirs på forskellige måder. Disse algoritmer sigter mod at minimere straffe som følge af vandforsyningsproblemer og lave reservoirlagre. De er effektive til at udlede driftsregler for enkelt- og multi-reservoirsystemer, og kan endda bruges til realtidsdrift og til at håndtere klimaændringers indvirkning. Alt i alt giver genetiske algoritmer en robust og effektiv måde at optimere fordeling og styring af vandressourcer i komplekse reservoirs."},"bots":{"critic":{"en":null,"da":null},"potential":{"en":null,"da":null}}}