{"id":"c144","number":2024,"headline":{"en":"Cancer detection algorithms","da":"Algoritmer til kræftdetektion"},"content":{"en":"Cancer detection algorithms: Scientists have been exploring the use of algorithms in detecting various types of cancer through surface-enhanced Raman spectroscopy. By combining this technique with different statistical and machine learning algorithms such as principal component analysis, support vector machine, and linear discriminant analysis, researchers aim to accurately diagnose and predict different types of cancer, including colorectal, gastric, esophageal, prostate, bladder, oral squamous cell carcinoma, nasopharyngeal, liver, lung, breast, and gallbladder cancer. These algorithms analyze the Raman spectra of blood serum or plasma samples to identify specific cancer markers, offering a potential non-invasive and efficient method for cancer detection.","da":"Algoritmer til kræftdetektion: Forskere har undersøgt brugen af algoritmer til at detektere forskellige typer af kræft gennem overfladeforstærket Raman-spektroskopi. Ved at kombinere denne teknik med forskellige statistiske og maskinlæringsalgoritmer såsom principal komponentanalyse, support vector maskine og lineær diskriminantanalyse, sigter forskerne mod nøjagtigt at diagnosticere og forudsige forskellige typer af kræft, herunder kolorektal, gastrisk, esophageal, prostata, blære, oral pladecellekarcinom, nasopharyngeal, lever, lunge, bryst og galdeblærekræft. Disse algoritmer analyserer Raman-spektret af blodserum eller plasma prøver for at identificere specifikke kræftmarkører, hvilket tilbyder en potentiel ikke-invasiv og effektiv metode til kræftdetektion."},"bots":{"critic":{"en":null,"da":null},"potential":{"en":null,"da":null}}}