{"id":"c1502","number":2617,"headline":{"en":"Pandemic data analysis","da":"Pandemidataanalyse"},"content":{"en":"Pandemic data analysis: Scientists are using various algorithms to understand and control the COVID-19 pandemic. They are using interpretable machine learning algorithms, mathematical models, artificial intelligence, and other techniques to answer questions such as the factors contributing to the control of COVID-19, predicting the spread of the virus, understanding the impact of physical distancing policies, and forecasting the number of cases in different countries. These algorithms are helping researchers analyze data and make informed decisions to manage the pandemic effectively.","da":"Pandemidataanalyse: Forskere bruger forskellige algoritmer for at forstå og kontrollere COVID-19-pandemien. De bruger forståelige maskinlæringsalgoritmer, matematiske modeller, kunstig intelligens og andre teknikker til at besvare spørgsmål som de faktorer, der bidrager til kontrol af COVID-19, forudsige spredningen af virusset, forstå virkningen af fysiske afstandspolitikker og forudsige antallet af tilfælde i forskellige lande. Disse algoritmer hjælper forskere med at analysere data og træffe informerede beslutninger for effektivt at håndtere pandemien."},"bots":{"critic":{"en":null,"da":null},"potential":{"en":null,"da":null}}}