{"id":"c1545","number":1452,"headline":{"en":"Auditory attention decoding","da":"Auditorisk opmærksomhedsafkodning"},"content":{"en":"Auditory attention decoding: Researchers have been investigating how algorithms can improve our ability to detect and decode auditory attention. They have explored the influence of head-related filtering and ear-specific decoding, as well as the combination of single-channel speech separation algorithms with auditory attention decoding. By using techniques such as EEG and MEG, these algorithms can track and decode selective auditory attention in real-time, potentially leading to advancements in neuro-steered hearing devices and improving our understanding of how we process sound.","da":"Auditorisk opmærksomhedsafkodning: Forskere har undersøgt, hvordan algoritmer kan forbedre vores evne til at opdage og afkode auditorisk opmærksomhed. De har udforsket indflydelsen af hovedrelateret filtrering og ørespecifik afkodning samt kombinationen af enkeltkanals taleadskillelsesalgoritmer med auditorisk opmærksomhedsafkodning. Ved hjælp af teknikker såsom EEG og MEG kan disse algoritmer spore og afkode selektiv auditorisk opmærksomhed i realtid, hvilket potentielt kan føre til fremskridt inden for neurostyrede høreapparater og forbedre vores forståelse af, hvordan vi bearbejder lyd."},"bots":{"critic":{"en":null,"da":null},"potential":{"en":null,"da":null}}}