{"id":"c1624","number":2909,"headline":{"en":"Spelling correction algorithms","da":"Stavningskorrektionsalgoritmer"},"content":{"en":"Spelling correction algorithms: Researchers have explored the use of algorithms to improve spelling correction in various languages, including English, Slovak, Hindi, Bangla, Chinese, and Amazigh. These algorithms have been found to detect and correct spelling errors with high accuracy, outperforming other systems and approaches. By using statistical methods, hybrid approaches, and post-processing operations, these algorithms offer promising solutions for improving the quality of written language in different contexts.","da":"Stavningskorrektionsalgoritmer: Forskere har undersøgt brugen af algoritmer til at forbedre stavningskorrektion på forskellige sprog, herunder engelsk, slovakisk, hindi, bangla, kinesisk og amazigh. Disse algoritmer har vist sig at kunne opdage og rette stavefejl med høj præcision og overgå andre systemer og metoder. Ved hjælp af statistiske metoder, hybride tilgange og efterbehandlingsoperationer tilbyder disse algoritmer lovende løsninger til at forbedre kvaliteten af det skrevne sprog i forskellige sammenhænge."},"bots":{"critic":{"en":null,"da":null},"potential":{"en":null,"da":null}}}