{"id":"c1744","number":86,"headline":{"en":"Defect detection algorithms","da":"Algoritmer til detektering af defekter"},"content":{"en":"Defect detection algorithms: Researchers have been exploring the use of algorithms to detect and classify defects in various industrial processes. These algorithms, often based on machine vision and image processing techniques, are capable of automatically identifying defects on finished surfaces, leadframes, weld surfaces, steel coils, and other materials. By combining computer vision approaches with pre-processing techniques and other technologies, these algorithms have the potential to significantly improve the efficiency and accuracy of defect detection in manufacturing processes.","da":"Algoritmer til detektering af defekter: Forskere har undersøgt brugen af algoritmer til at detektere og klassificere defekter i forskellige industrielle processer. Disse algoritmer, som ofte er baseret på maskinsyn og billedbehandlingsteknikker, er i stand til automatisk at identificere defekter på færdige overflader, leadframes, svejseoverflader, stålruller og andre materialer. Ved at kombinere computer vision-tilgange med forbehandlingsteknikker og andre teknologier har disse algoritmer potentialet til betydeligt at forbedre effektiviteten og nøjagtigheden af defektdetektion i fremstillingsprocesser."},"bots":{"critic":{"en":null,"da":null},"potential":{"en":null,"da":null}}}