{"id":"c2006","number":320,"headline":{"en":"Wind farm optimization","da":"Optimering af vindmølleparker"},"content":{"en":"Wind farm optimization: Researchers are using algorithms to optimize the layout of wind farms in order to maximize energy capture and improve overall efficiency. These algorithms, such as multi-objective evolutionary strategies and genetic algorithms, analyze different wind conditions and optimize the placement of wind turbines. By considering factors like stochastic loading, wake losses, noise impact, and wake-induced turbulence, these algorithms help design wind farms that produce more energy while minimizing costs and environmental impact.","da":"Optimering af vindmølleparker: Forskere bruger algoritmer til at optimere layoutet af vindmølleparker for at maksimere energifangsten og forbedre den overordnede effektivitet. Disse algoritmer, såsom multi-objektive evolutionære strategier og genetiske algoritmer, analyserer forskellige vindforhold og optimerer placeringen af vindmøller. Ved at tage højde for faktorer som stokastisk belastning, wake-tab, støjpåvirkning og wake-induceret turbulens hjælper disse algoritmer med at designe vindmølleparker, der producerer mere energi, samtidig med at omkostninger og miljøpåvirkning minimeres."},"bots":{"critic":{"en":null,"da":null},"potential":{"en":null,"da":null}}}