{"id":"c2046","number":563,"headline":{"en":"Structural system analysis","da":"Strukturel systemsanalyse"},"content":{"en":"Structural system analysis: Researchers have been investigating the capabilities of various algorithms in accurately identifying and assessing the properties and damages of structural systems. These algorithms, such as maximum likelihood estimation, finite element-based techniques, adaptive on-line identification, and Kalman filter-based strategies, are able to achieve accurate results by matching model responses with measured responses, considering both viscous and Rayleigh-type damping, and tracking changes in structural parameters even with unknown inputs and outputs. By combining different algorithms and methods, researchers have been able to improve the accuracy and efficiency of structural system parameter identification and damage assessment.","da":"Strukturel systemsanalyse: Forskere har undersøgt egenskaberne ved forskellige algoritmer til præcist at identificere og vurdere egenskaber og skader på strukturelle systemer. Disse algoritmer, såsom maksimal sandsynlighedsestimation, finite element-baserede teknikker, adaptiv online-identifikation og Kalman filter-baserede strategier, kan opnå nøjagtige resultater ved at matche modelresponser med målte responser, tage hensyn til både viskøs og Rayleigh-type dæmpning og følge ændringer i strukturelle parametre selv med ukendte input og output. Ved at kombinere forskellige algoritmer og metoder har forskere været i stand til at forbedre nøjagtigheden og effektiviteten af identifikationen af strukturelle systemparametre og skadevurdering."},"bots":{"critic":{"en":null,"da":null},"potential":{"en":null,"da":null}}}