{"id":"c2063","number":313,"headline":{"en":"Energy forecasting","da":"Energiforudsigelse"},"content":{"en":"Energy forecasting: Deep learning algorithms, such as LSTM and GRU, have been found to accurately forecast various aspects of energy consumption and demand. These algorithms outperform other traditional forecasting methods and can accurately predict short-term load, electricity demand, and energy consumption for both residential and industrial sectors. The use of deep learning techniques in energy forecasting shows promise in improving the efficiency and sustainability of energy systems.","da":"Energiforudsigelse: Deep learning-algoritmer, såsom LSTM og GRU, har vist sig at med stor nøjagtighed kunne forudsige forskellige aspekter af energiforbrug og efterspørgsel. Disse algoritmer overgår andre traditionelle forudsigelsesmetoder og kan præcist forudsige kortvarig belastning, elektricitetsbehov og energiforbrug i både beboelses- og industrisektorerne. Brugen af deep learning-teknikker i energiforudsigelse viser lovende resultater med hensyn til at forbedre effektiviteten og bæredygtigheden af energisystemer."},"bots":{"critic":{"en":null,"da":null},"potential":{"en":null,"da":null}}}