{"id":"c228","number":1561,"headline":{"en":"Image retrieval advancements","da":"Fremskridt inden for billedgenfinding"},"content":{"en":"Image retrieval advancements: Researchers are exploring ways to improve content-based image retrieval using algorithms. These algorithms are being used to extract color and texture features, cluster color blocks, compute similarity distance, and extract rotation-invariant Gabor texture features. They are also being used for feature extraction, discrimination, and selection, as well as the extraction of local statistical color moment features and the combination of color and shape features.","da":"Fremskridt inden for billedgenfinding: Forskere undersøger måder at forbedre indholdsbaseret billedgenfinding ved hjælp af algoritmer. Disse algoritmer bruges til at udtrække farve- og teksturtræk, gruppere farveblokke, beregne lighedsafstand og udtrække rotationsinvariante Gabor-teksturtræk. De bruges også til træksudtrækning, diskrimination og udvælgelse samt udtrækning af lokale statistiske farvemomenter og kombinationen af ​​farve- og formtræk."},"bots":{"critic":{"en":null,"da":null},"potential":{"en":null,"da":null}}}