{"id":"c2343","number":126,"headline":{"en":"Electromagnetic modeling","da":"Elektromagnetisk modellering"},"content":{"en":"Electromagnetic modeling: Researchers have developed new algorithms to address various challenges in modeling and simulating complex electromagnetic systems. These algorithms, such as the two-step Lanczos algorithm and the partial realization method, enable efficient model order reduction and passivity enforcement in interconnect networks. They also allow for the generation of large-scale macromodels and accurate simulation models for high-speed interconnects.","da":"Elektromagnetisk modellering: Forskere har udviklet nye algoritmer til at imødegå forskellige udfordringer i modellering og simulering af komplekse elektromagnetiske systemer. Disse algoritmer, såsom totrins Lanczos-algoritmen og metoden for delvis realisering, muliggør effektiv reduktion af modelordrer og håndhævelse af passivitet i forbindelsesnetværk. De tillader også generering af store makromodeller og præcise simuleringsmodeller for højhastighedsforbindelser."},"bots":{"critic":{"en":null,"da":null},"potential":{"en":null,"da":null}}}