{"id":"c2620","number":3297,"headline":{"en":"Satellite optimization","da":"Satellitoptimering"},"content":{"en":"Satellite optimization: Researchers are exploring how deep reinforcement learning algorithms can be used to optimize various aspects of satellite communication systems. These algorithms, such as the Deep reinforcement learning-based framework (DRLF) and the Deep-Q-network (DQN) controller, are being applied to tasks like resource allocation, power allocation, and user association. By using these advanced machine learning techniques, scientists hope to improve the efficiency and performance of satellite networks, ultimately enhancing our ability to communicate and access information from space.","da":"Satellitoptimering: Forskere undersøger, hvordan dyb forstærkningslæringsalgoritmer kan bruges til at optimere forskellige aspekter af satellitkommunikationssystemer. Disse algoritmer, såsom den dyb forstærkningslæringsbaserede ramme (DRLF) og Deep-Q-netværkskontrolleren (DQN), anvendes på opgaver som ressourceallokering, strømfordeling og brugerassociation. Ved at bruge disse avancerede maskinlæringsteknikker håber videnskabsfolk at forbedre effektiviteten og ydeevnen af satellitnetværk, hvilket i sidste ende vil forbedre vores evne til at kommunikere og få adgang til information fra rummet."},"bots":{"critic":{"en":null,"da":null},"potential":{"en":null,"da":null}}}