{"id":"c2678","number":2307,"headline":{"en":"Blood donor screening","da":"Bloddonor screening"},"content":{"en":"Blood donor screening: A set of scientific abstracts analyzed the use of algorithms in screening blood donors for infectious diseases like HIV, HCV, and HBV. The research questions focused on comparing different high-throughput strategies, evaluating the efficacy of individual NAT (nucleic acid testing), and estimating the prevalence of occult HBV infection. The algorithms mentioned include the Chiron Piocleix HIV-1/HCV TMA assay, Roche and Chiron/Gen-Probe triplex assays, Procleix Tigris and cobas s 201 systems, and CE-marked nucleic acid tests.","da":"Bloddonor screening: Et sæt videnskabelige abstracts analyserede brugen af algoritmer ved screening af bloddonorer for infektionssygdomme som HIV, HCV og HBV. Forskningsspørgsmålene fokuserede på at sammenligne forskellige højkapacitetsstrategier, evaluere effektiviteten af individuel NAT (nukleinsyreametest) og estimere prævalensen af okkult HBV-infektion. De nævnte algoritmer inkluderer Chiron Piocleix HIV-1/HCV TMA-assay, Roche og Chiron/Gen-Probe triplex assays, Procleix Tigris og cobas s 201-systemerne samt CE-mærkede nukleinsyreametoder."},"bots":{"critic":{"en":null,"da":null},"potential":{"en":null,"da":null}}}