{"id":"c2868","number":3661,"headline":{"en":"Facility layout optimization","da":"Optimering af facilitetslayout"},"content":{"en":"Facility layout optimization: Researchers have been exploring various approaches to solve facility layout problems, such as the multi-floor facility layout problem and the single-row facility layout problem. Algorithms are being used to evaluate the effectiveness of different approaches, provide state-of-the-art reviews, develop solution approaches, and propose optimization methods. These algorithms play a crucial role in improving facility layout planning and finding efficient solutions for complex problems.","da":"Optimering af facilitetslayout: Forskere har undersøgt forskellige tilgange til at løse problemer med facilitetslayout, såsom multiflors facilitetslayoutproblem og enkelt-rækkes facilitetslayoutproblem. Algoritmer bliver brugt til at evaluere effektiviteten af forskellige tilgange, levere state-of-the-art anmeldelser, udvikle løsningsmetoder og foreslå optimeringsmetoder. Disse algoritmer spiller en afgørende rolle i at forbedre facilitetslayoutplanlægning og finde effektive løsninger på komplekse problemer."},"bots":{"critic":{"en":null,"da":null},"potential":{"en":null,"da":null}}}