{"id":"c3123","number":1189,"headline":{"en":"Polymer property prediction","da":"Polymer egenskabsforudsigelse"},"content":{"en":"Polymer property prediction: Scientists are exploring the use of machine learning algorithms to accelerate the discovery and design of new polymers with specific properties. These algorithms can predict the thermal conductivity, glass transition temperature, and other physical properties of polymers based on their molecular structures. By combining machine learning with high-throughput experimentation and simulations, researchers hope to revolutionize the field of polymer science and create new materials for various applications, including biomaterials and nanocomposites.","da":"Polymer egenskabsforudsigelse: Forskere undersøger brugen af maskinlæringsalgoritmer til at fremskynde opdagelsen og designet af nye polymerer med specifikke egenskaber. Disse algoritmer kan forudsige den termiske ledningsevne, glastemperatur og andre fysiske egenskaber for polymerer baseret på deres molekylære strukturer. Ved at kombinere maskinlæring med høj-gennemløbseksperimentation og simuleringer håber forskerne at revolutionere polymervidenskaben og skabe nye materialer til forskellige anvendelser, herunder biomaterialer og nanokompositter."},"bots":{"critic":{"en":null,"da":null},"potential":{"en":null,"da":null}}}