{"id":"c321","number":2585,"headline":{"en":"EEG analysis advancements","da":"Fremskridt inden for EEG-analyse"},"content":{"en":"EEG analysis advancements: Scientists have been exploring various algorithms to improve the analysis of EEG and ERP data. These algorithms, such as Independent Component Analysis (ICA), Blind Source Separation (BSS), and Linear Discriminant Analysis (LDA), are used to enhance the localization of brain activity, identify different components in the data, and classify artifacts. Additionally, machine learning methods and automated tools like FASTER and ADJUST have been developed to automate the detection and rejection of EEG artifacts. These advancements in algorithmic analysis are helping researchers gain a deeper understanding of brain activity and improve the accuracy of EEG and ERP studies.","da":"Fremskridt inden for EEG-analyse: Forskere har undersøgt forskellige algoritmer for at forbedre analysen af EEG- og ERP-data. Disse algoritmer, såsom Uafhængig Komponentanalyse (ICA), Blind Kildeadskillelse (BSS) og Lineær Diskriminantanalyse (LDA), anvendes til at forbedre lokaliseringen af ​​hjerneaktivitet, identificere forskellige komponenter i dataene og klassificere artefakter. Derudover er maskinlæringsmetoder og automatiserede værktøjer som FASTER og ADJUST blevet udviklet til at automatisere detektion og afvisning af EEG-artefakter. Disse fremskridt inden for algoritmisk analyse hjælper forskere med at opnå en dybere forståelse af hjerneaktivitet og forbedre nøjagtigheden af ​​EEG- og ERP-studier."},"bots":{"critic":{"en":null,"da":null},"potential":{"en":null,"da":null}}}