{"id":"c3305","number":1055,"headline":{"en":"Capture-Recapture Algorithms","da":"Capture-Recapture Algoritmer"},"content":{"en":"Capture-Recapture Algorithms: Scientists have developed algorithms to address various research questions in the field of capture-recapture studies. These algorithms are used to estimate population size, model capture-recapture data with heterogeneity, improve population estimation in mark-recapture experiments, and analyze complex capture-recapture data with covariates and model uncertainty. The algorithms employ techniques such as conditional probabilities, maximum likelihood estimation, Bayesian approaches, and Monte Carlo methods to handle the complexity of the data and improve accuracy in population estimation.","da":"Capture-Recapture Algoritmer: Forskere har udviklet algoritmer til at besvare forskellige forskningsspørgsmål inden for capture-recapture studier. Disse algoritmer anvendes til at estimere populationsstørrelse, modellere capture-recapture data med heterogenitet, forbedre populationsestimation i mark-recapture eksperimenter og analysere komplekse capture-recapture data med kovariater og modelusikkerhed. Algoritmerne anvender teknikker som betingede sandsynligheder, maximum likelihood estimation, Bayesian tilgange og Monte Carlo metoder til at håndtere dataenes kompleksitet og forbedre nøjagtigheden i populationsestimation."},"bots":{"critic":{"en":null,"da":null},"potential":{"en":null,"da":null}}}