{"id":"c35","number":3984,"headline":{"en":"Sensor fusion optimization","da":"Sensor fusion-optimering"},"content":{"en":"Sensor fusion optimization: Researchers are exploring the use of algorithms to improve the accuracy and performance of various sensor fusion systems. These algorithms are being used to combine measurements from LiDAR, inertial sensors, and visual cameras, enabling better state estimation and navigation in different scenarios. By optimizing the matching accuracy of LiDAR, compensating for motion distortion, and fusing data from multiple sensors, these algorithms aim to enhance the localization and mapping capabilities of autonomous systems.","da":"Sensor fusion-optimering: Forskere undersøger brugen af algoritmer til at forbedre nøjagtigheden og ydeevnen af forskellige sensorfusionssystemer. Disse algoritmer bliver brugt til at kombinere målinger fra LiDAR, inertielle sensorer og visuelle kameraer, hvilket muliggør bedre tilstandsestimering og navigation i forskellige scenarier. Ved at optimere LiDAR's matchingsnøjagtighed, kompensere for bevægelsesforvrængning og flette data fra flere sensorer, sigter disse algoritmer mod at forbedre lokaliserings- og kortlægningsfunktionerne for autonome systemer."},"bots":{"critic":{"en":null,"da":null},"potential":{"en":null,"da":null}}}