{"id":"c3622","number":67,"headline":{"en":"Meta-optimization","da":"Meta-optimering"},"content":{"en":"Meta-optimization: Researchers are exploring the use of algorithms to optimize the design of metasurfaces in order to reduce radar cross section (RCS). These metasurfaces, made up of tiny elements, can potentially make objects less detectable by radar. Algorithms such as genetic algorithms, particle swarm optimization, and evolutionary algorithms are being used to find the best arrangement and coding sequence for these metasurfaces, allowing for wideband and broadband RCS reduction.","da":"Meta-optimering: Forskere undersøger anvendelsen af algoritmer til at optimere designet af metasurface for at reducere radar tværsnitsareal (RCS). Disse metasurface, der består af små elementer, kan potentielt gøre objekter mindre opdages af radar. Algoritmer som genetiske algoritmer, partikel-sværm optimering og evolutionære algoritmer anvendes til at finde den bedste arrangement og kodningssekvens for disse metasurface, hvilket tillader bredbånds- og bredspektrum RCS-reduktion."},"bots":{"critic":{"en":null,"da":null},"potential":{"en":null,"da":null}}}