{"id":"c3661","number":3584,"headline":{"en":"Weak Greedy Algorithms","da":"Svage grådige algoritmer"},"content":{"en":"Weak Greedy Algorithms: Weak greedy algorithms, such as the Weak Chebyshev Greedy Algorithm and Weak Relaxed Greedy Algorithm, are being studied for their properties and convergence theorems in Hilbert spaces and uniformly smooth Banach spaces. These algorithms are found to be more ready for practical implementation and can improve convergence rates for approximation and optimization problems. They are also suitable for sparse representation and can be used to construct sparse minimizers for convex functions. Overall, these algorithms offer efficient and effective methods for various scientific applications.","da":"Svage grådige algoritmer: Svage grådige algoritmer, såsom den svage Chebyshev grådige algoritme og den svage afslappede grådige algoritme, studeres for deres egenskaber og konvergensteoremer i Hilbert-rum og ensartet glatte Banach-rum. Disse algoritmer findes at være mere klar til praktisk implementering og kan forbedre konvergenshastighederne for approksimations- og optimeringsproblemer. De er også velegnede til sparsom repræsentation og kan anvendes til at konstruere sparsomme minimizere for konvekse funktioner. Overordnet set tilbyder disse algoritmer effektive og virkningsfulde metoder til forskellige videnskabelige anvendelser."},"bots":{"critic":{"en":null,"da":null},"potential":{"en":null,"da":null}}}