{"id":"c369","number":3025,"headline":{"en":"Expert Systems","da":"Ekspertsystemer"},"content":{"en":"Expert Systems: Expert systems are new tools that can be used in professional decision-making and provide a means of solving complex problems through automation. They emulate human reasoning and use artificial intelligence techniques to provide expert opinions for specialized problem areas. While they can improve decision making, they also have limitations as a form of artificial intelligence. Overall, expert systems are widely applicable and can be developed, operated, and applied for expert decision making in various fields.","da":"Ekspertsystemer: Ekspertsystemer er nye værktøjer, der kan bruges i professionel beslutningstagning og giver en metode til at løse komplekse problemer gennem automatisering. De efterligner menneskelig ræsonnering og bruger teknikker inden for kunstig intelligens til at levere ekspertudtalelser for specialiserede problemområder. Selvom de kan forbedre beslutningstagning, har de også begrænsninger som en form for kunstig intelligens. Overordnet set er ekspertsystemer bredt anvendelige og kan udvikles, opereres og anvendes til eksperbeslutninger på forskellige områder."},"bots":{"critic":{"en":null,"da":null},"potential":{"en":null,"da":null}}}