{"id":"c3804","number":1199,"headline":{"en":"Polarization Imaging Algorithms","da":"Polarisationsbilleddannelsesalgoritmer"},"content":{"en":"Polarization Imaging Algorithms: Researchers have been exploring the use of algorithms to improve various aspects of imaging techniques that involve polarization. For example, algorithms have been developed to estimate polarization parameters, maximize polarimetric contrast, improve image contrast in turbid media, remove specularity without color distortions, mitigate noise in imaging polarimetry, and extract polarization features for target detection. These algorithms aim to enhance the accuracy, quality, and performance of polarization imaging in different conditions and applications.","da":"Polarisationsbilleddannelsesalgoritmer: Forskere har undersøgt brugen af algoritmer til at forbedre forskellige aspekter af billeddannelse, der involverer polarisering. For eksempel er der udviklet algoritmer til at estimere polarisationsparametre, maksimere polarimetrisk kontrast, forbedre billedkontrast i uklare medier, fjerne spekularitet uden farveforvrængninger, mindske støj i billedpolarimetri og udtrække polarisationsfunktioner til måldetektion. Disse algoritmer har til formål at forbedre nøjagtigheden, kvaliteten og ydeevnen af polarisationsbilleddannelse under forskellige forhold og anvendelser."},"bots":{"critic":{"en":null,"da":null},"potential":{"en":null,"da":null}}}