{"id":"c3980","number":3519,"headline":{"en":"Matroid algorithm advancements","da":"Fremskridt inden for matroidalgoritmer"},"content":{"en":"Matroid algorithm advancements: Researchers have been investigating various aspects of algorithms in the field of matroid theory. They have explored efficient algorithms for linear matroid intersection problems, properties of Δ-matroids induced by simple graphs, and the application of matroid algorithms to optimization problems on graphs. These studies have resulted in the development of algorithms for finding independent sets, determining minimum weight bases, and analyzing the performance of greedy algorithms in matroids.","da":"Fremskridt inden for matroidalgoritmer: Forskere har undersøgt forskellige aspekter af algoritmer inden for matroidteori. De har udforsket effektive algoritmer til lineære matroidskæringsproblemer, egenskaber af Δ-matroider fremkaldt af simple grafer, og anvendelsen af matroidalgoritmer til optimeringsproblemer på grafer. Disse studier har resulteret i udviklingen af algoritmer til at finde uafhængige sæt, bestemme minimumsvægtbaser og analysere ydelsen af grådige algoritmer i matroider."},"bots":{"critic":{"en":null,"da":null},"potential":{"en":null,"da":null}}}