{"id":"c4047","number":1639,"headline":{"en":"Genetic trait analysis","da":"Genetisk egenskabsanalyse"},"content":{"en":"Genetic trait analysis: Scientists have used various algorithms to investigate the genetic parameters and factors influencing the growth and performance traits of different sheep and cattle breeds. These algorithms, such as Restricted Maximum Likelihood methods and Derivative-free algorithms, help researchers estimate the heritability and variance components of these traits. By understanding the genetic and non-genetic factors affecting these animals, scientists can make informed decisions to improve their growth and productivity.","da":"Genetisk egenskabsanalyse: Forskere har brugt forskellige algoritmer til at undersøge de genetiske parametre og faktorer, der påvirker vækst- og præstationsegenskaberne hos forskellige får- og kvægracer. Disse algoritmer, såsom Restricted Maximum Likelihood-metoder og Derivative-free algoritmer, hjælper forskere med at estimere arvelighed og varianskomponenterne af disse egenskaber. Ved at forstå de genetiske og ikke-genetiske faktorer, der påvirker disse dyr, kan forskere træffe informerede beslutninger for at forbedre deres vækst og produktivitet."},"bots":{"critic":{"en":null,"da":null},"potential":{"en":null,"da":null}}}