{"id":"c4090","number":846,"headline":{"en":"Earthquake prediction","da":"Jordskælvsprediktion"},"content":{"en":"Earthquake prediction: Scientists have developed algorithms that can predict earthquakes with varying degrees of accuracy. One algorithm, called M8, has been successfully used to predict intermediate-term earthquakes in Greece and the strongest earthquakes in different regions of the world. Another algorithm, CN, can diagnose times of increased probability of strong earthquakes in various regions. These algorithms have the potential to prevent damage and save lives by allowing for early warning systems.","da":"Jordskælvsprediktion: Forskere har udviklet algoritmer, der kan forudsige jordskælv med varierende grad af nøjagtighed. En algoritme kaldet M8 er blevet brugt med succes til at forudsige mellemlange jordskælv i Grækenland og de stærkeste jordskælv i forskellige regioner af verden. En anden algoritme, CN, kan diagnosticere tidspunkter med øget sandsynlighed for stærke jordskælv i forskellige regioner. Disse algoritmer har potentialet til at forhindre skader og redde liv ved at muliggøre tidlige varslingssystemer."},"bots":{"critic":{"en":null,"da":null},"potential":{"en":null,"da":null}}}