{"id":"c410","number":1795,"headline":{"en":"Livestock behavior monitoring","da":"Overvågning af husdyradfærd"},"content":{"en":"Livestock behavior monitoring: Researchers have been investigating the use of algorithms and advanced technologies to monitor and predict behaviors in livestock. For example, an accelerometer attached to an ear tag can accurately estimate feeding and rumination time in feedlot cattle. Automated health-monitoring systems based on rumination time and physical activity can identify dairy cows with metritis, mastitis, and other disorders. Machine learning algorithms are used to analyze data from sensors and monitors to predict calving, bull behavior, and respiratory disease in cattle. These technologies offer valuable insights into animal health and behavior, improving the management and well-being of livestock.","da":"Overvågning af husdyradfærd: Forskere har undersøgt brugen af algoritmer og avancerede teknologier til at overvåge og forudsige adfærd hos husdyr. For eksempel kan et accelerometer, der er fastgjort til et øremærke, præcist estimere fodrings- og tyggetid hos slagtekvæg. Automatiserede sundhedsovervågningssystemer baseret på tyggetid og fysisk aktivitet kan identificere malkekøer med metritis, mastitis og andre lidelser. Maskinlæringsalgoritmer anvendes til at analysere data fra sensorer og overvågningsudstyr for at forudsige kælvning, tyreadfærd og luftvejssygdomme hos kvæg. Disse teknologier tilbyder værdifuld indsigt i dyrenes sundhed og adfærd, hvilket forbedrer forvaltningen og velfærden af husdyr."},"bots":{"critic":{"en":null,"da":null},"potential":{"en":null,"da":null}}}