{"id":"c516","number":675,"headline":{"en":"Injection Molding Optimization","da":"Optimering af sprøjtestøbning"},"content":{"en":"Injection Molding Optimization: Researchers have developed various algorithms to solve complex problems in injection molding. These algorithms involve solving equations related to momentum, mass, and energy conservation, as well as the Navier-Stokes equation. They also use methods like finite element, finite volume, and arbitrary Lagrangian-Eulerian (ALE) to accurately simulate the filling and packing stages of injection molding. These algorithms help improve the efficiency and accuracy of the injection molding process.","da":"Optimering af sprøjtestøbning: Forskere har udviklet forskellige algoritmer til at løse komplekse problemer inden for sprøjtestøbning. Disse algoritmer involverer løsning af ligninger relateret til momentum-, masse- og energibevarelse samt Navier-Stokes ligningen. De anvender også metoder som finit element, finit volumen og arbitrær Lagrangian-Euler (ALE) for nøjagtigt at simulere fyldnings- og pakkestadierne i sprøjtestøbningsprocessen. Disse algoritmer hjælper med at forbedre effektiviteten og nøjagtigheden af sprøjtestøbningsprocessen."},"bots":{"critic":{"en":null,"da":null},"potential":{"en":null,"da":null}}}