{"id":"c854","number":34,"headline":{"en":"3D Shape Reconstruction","da":"3D-formrekonstruktion"},"content":{"en":"3D Shape Reconstruction: Researchers have developed algorithms that can reconstruct the 3D shape of objects using multiple viewpoints and changing illumination conditions. These algorithms use a combination of geometric and photometric information to accurately compute the shape and texture of the objects. The algorithms have been applied to various applications, such as creating high-quality 3D models and reconstructing ultra-large-scale scenes.","da":"3D-formrekonstruktion: Forskere har udviklet algoritmer, der kan rekonstruere objekters 3D-form ved hjælp af flere synspunkter og skiftende belysningsforhold. Disse algoritmer bruger en kombination af geometrisk og fotometrisk information til præcist at beregne objekternes form og tekstur. Algoritmerne er blevet anvendt til forskellige anvendelser, såsom at skabe høj-kvalitets 3D-modeller og rekonstruere ultra-storskala scener."},"bots":{"critic":{"en":null,"da":null},"potential":{"en":null,"da":null}}}