{"id":"c876","number":1531,"headline":{"en":"Face recognition algorithms","da":"Ansigtsgenkendelsesalgoritmer"},"content":{"en":"Face recognition algorithms: Researchers have been exploring various algorithms to improve face recognition. These algorithms, such as 2DPCA, modified PCA, KCCA-based feature extraction, and non-negative principal component analysis, aim to enhance the efficiency and accuracy of face recognition systems. By combining different techniques, researchers have achieved better computational efficiency, reduced feature vector size, and improved recognition rates. These advancements in algorithm development have the potential to greatly benefit the field of face recognition.","da":"Ansigtsgenkendelsesalgoritmer: Forskere har undersøgt forskellige algoritmer for at forbedre ansigtsgenkendelse. Disse algoritmer, såsom 2DPCA, modificeret PCA, KCCA-baseret feature-ekstraktion og ikke-negativ hovedkomponentanalyse, har til formål at øge effektiviteten og nøjagtigheden af ansigtsgenkendelsessystemer. Ved at kombinere forskellige teknikker har forskerne opnået bedre computerberegningseffektivitet, reduceret featurevektorstørrelse og forbedrede genkendelsesrater. Disse fremskridt inden for algoritmeudvikling har potentiale til at gavne feltet for ansigtsgenkendelse betydeligt."},"bots":{"critic":{"en":null,"da":null},"potential":{"en":null,"da":null}}}